[
	{
		"date": "2020-10-30T07:24:44.000Z",
		"cases": 57002,
		"dailyCases": 282,
		"cumuCases": 57002
	},
	{
		"date": "2020-10-31T07:36:19.000Z",
		"cases": 57284,
		"dailyCases": 282,
		"cumuCases": 57284
	},
	{
		"date": "2020-11-01T08:25:04.000Z",
		"cases": 57407,
		"dailyCases": 123,
		"cumuCases": 57407
	},
	{
		"date": "2020-11-02T09:00:16.000Z",
		"cases": 57488,
		"dailyCases": 81,
		"cumuCases": 57488
	},
	{
		"date": "2020-11-03T08:25:09.000Z",
		"cases": 57624,
		"dailyCases": 136,
		"cumuCases": 57624
	},
	{
		"date": "2020-11-04T09:05:03.000Z",
		"cases": 57789,
		"dailyCases": 165,
		"cumuCases": 57789
	},
	{
		"date": "2020-11-05T08:24:55.000Z",
		"cases": 57789,
		"dailyCases": 0,
		"cumuCases": 57789
	},
	{
		"date": "2020-11-06T08:24:52.000Z",
		"cases": 58684,
		"dailyCases": 895,
		"cumuCases": 58684
	},
	{
		"date": "2020-11-07T08:24:56.000Z",
		"cases": 59065,
		"dailyCases": 381,
		"cumuCases": 59065
	},
	{
		"date": "2020-11-08T08:25:45.000Z",
		"cases": 59189,
		"dailyCases": 124,
		"cumuCases": 59189
	},
	{
		"date": "2020-11-09T08:40:07.000Z",
		"cases": 59195,
		"dailyCases": 6,
		"cumuCases": 59195
	},
	{
		"date": "2020-11-10T08:25:30.000Z",
		"cases": 59273,
		"dailyCases": 78,
		"cumuCases": 59273
	},
	{
		"date": "2020-11-11T08:25:55.000Z",
		"cases": 59586,
		"dailyCases": 313,
		"cumuCases": 59586
	},
	{
		"date": "2020-11-12T08:25:30.000Z",
		"cases": 59946,
		"dailyCases": 360,
		"cumuCases": 59946
	},
	{
		"date": "2020-11-13T08:25:37.000Z",
		"cases": 60156,
		"dailyCases": 210,
		"cumuCases": 60156
	},
	{
		"date": "2020-11-14T08:26:53.000Z",
		"cases": 60416,
		"dailyCases": 260,
		"cumuCases": 60416
	},
	{
		"date": "2020-11-15T08:25:57.000Z",
		"cases": 60535,
		"dailyCases": 119,
		"cumuCases": 60535
	},
	{
		"date": "2020-11-16T08:25:54.000Z",
		"cases": 60579,
		"dailyCases": 44,
		"cumuCases": 60579
	},
	{
		"date": "2020-11-17T08:40:31.000Z",
		"cases": 60790,
		"dailyCases": 211,
		"cumuCases": 60790
	},
	{
		"date": "2020-11-18T08:25:23.000Z",
		"cases": 61001,
		"dailyCases": 211,
		"cumuCases": 61001
	},
	{
		"date": "2020-11-19T08:26:28.000Z",
		"cases": 61245,
		"dailyCases": 244,
		"cumuCases": 61245
	},
	{
		"date": "2020-11-20T08:25:51.000Z",
		"cases": 61553,
		"dailyCases": 308,
		"cumuCases": 61553
	},
	{
		"date": "2020-11-21T08:25:45.000Z",
		"cases": 61744,
		"dailyCases": 191,
		"cumuCases": 61744
	},
	{
		"date": "2020-11-22T08:25:26.000Z",
		"cases": 61838,
		"dailyCases": 94,
		"cumuCases": 61838
	},
	{
		"date": "2020-11-23T08:27:31.000Z",
		"cases": 62015,
		"dailyCases": 177,
		"cumuCases": 62015
	},
	{
		"date": "2020-11-24T08:27:20.000Z",
		"cases": 62139,
		"dailyCases": 124,
		"cumuCases": 62139
	},
	{
		"date": "2020-11-25T08:27:44.000Z",
		"cases": 62414,
		"dailyCases": 275,
		"cumuCases": 62414
	},
	{
		"date": "2020-11-26T08:26:53.000Z",
		"cases": 62603,
		"dailyCases": 189,
		"cumuCases": 62603
	},
	{
		"date": "2020-11-27T08:25:50.000Z",
		"cases": 62757,
		"dailyCases": 154,
		"cumuCases": 62757
	},
	{
		"date": "2020-11-28T08:25:55.000Z",
		"cases": 62816,
		"dailyCases": 59,
		"cumuCases": 62816
	},
	{
		"date": "2020-11-29T08:26:13.000Z",
		"cases": 63234,
		"dailyCases": 418,
		"cumuCases": 63234
	},
	{
		"date": "2020-11-30T08:26:18.000Z",
		"cases": 63322,
		"dailyCases": 88,
		"cumuCases": 63322
	},
	{
		"date": "2020-12-01T08:27:41.000Z",
		"cases": 63572,
		"dailyCases": 250,
		"cumuCases": 63572
	},
	{
		"date": "2020-12-02T08:28:22.000Z",
		"cases": 63899,
		"dailyCases": 327,
		"cumuCases": 63899
	},
	{
		"date": "2020-12-03T08:27:27.000Z",
		"cases": 64174,
		"dailyCases": 275,
		"cumuCases": 64174
	},
	{
		"date": "2020-12-04T08:27:36.000Z",
		"cases": 64317,
		"dailyCases": 143,
		"cumuCases": 64317
	},
	{
		"date": "2020-12-05T08:26:18.000Z",
		"cases": 64685,
		"dailyCases": 368,
		"cumuCases": 64685
	},
	{
		"date": "2020-12-06T08:26:14.000Z",
		"cases": 64905,
		"dailyCases": 220,
		"cumuCases": 64905
	},
	{
		"date": "2020-12-07T08:27:42.000Z",
		"cases": 65015,
		"dailyCases": 110,
		"cumuCases": 65015
	},
	{
		"date": "2020-12-08T08:28:01.000Z",
		"cases": 65084,
		"dailyCases": 69,
		"cumuCases": 65084
	},
	{
		"date": "2020-12-09T08:26:19.000Z",
		"cases": 65218,
		"dailyCases": 134,
		"cumuCases": 65218
	},
	{
		"date": "2020-12-10T08:26:59.000Z",
		"cases": 65595,
		"dailyCases": 377,
		"cumuCases": 65595
	},
	{
		"date": "2020-12-11T08:26:19.000Z",
		"cases": 65974,
		"dailyCases": 379,
		"cumuCases": 65974
	},
	{
		"date": "2020-12-12T08:27:20.000Z",
		"cases": 66221,
		"dailyCases": 247,
		"cumuCases": 66221
	},
	{
		"date": "2020-12-13T08:26:27.000Z",
		"cases": 66407,
		"dailyCases": 186,
		"cumuCases": 66407
	},
	{
		"date": "2020-12-14T08:26:38.000Z",
		"cases": 66454,
		"dailyCases": 47,
		"cumuCases": 66454
	},
	{
		"date": "2020-12-15T08:28:04.000Z",
		"cases": 66515,
		"dailyCases": 61,
		"cumuCases": 66515
	},
	{
		"date": "2020-12-16T08:28:12.000Z",
		"cases": 66574,
		"dailyCases": 59,
		"cumuCases": 66574
	},
	{
		"date": "2020-12-17T08:28:18.000Z",
		"cases": 66977,
		"dailyCases": 403,
		"cumuCases": 66977
	},
	{
		"date": "2020-12-18T08:27:52.000Z",
		"cases": 67184,
		"dailyCases": 207,
		"cumuCases": 67184
	},
	{
		"date": "2020-12-19T08:27:32.000Z",
		"cases": 67359,
		"dailyCases": 175,
		"cumuCases": 67359
	},
	{
		"date": "2020-12-20T08:27:58.000Z",
		"cases": 67429,
		"dailyCases": 70,
		"cumuCases": 67429
	},
	{
		"date": "2020-12-21T08:22:33.000Z",
		"cases": 67531,
		"dailyCases": 102,
		"cumuCases": 67531
	},
	{
		"date": "2020-12-22T08:22:03.000Z",
		"cases": 67686,
		"dailyCases": 155,
		"cumuCases": 67686
	},
	{
		"date": "2020-12-23T08:23:04.000Z",
		"cases": 67909,
		"dailyCases": 223,
		"cumuCases": 67909
	},
	{
		"date": "2020-12-24T08:22:48.000Z",
		"cases": 68107,
		"dailyCases": 198,
		"cumuCases": 68107
	},
	{
		"date": "2020-12-25T08:22:28.000Z",
		"cases": 68195,
		"dailyCases": 88,
		"cumuCases": 68195
	},
	{
		"date": "2020-12-26T08:22:55.000Z",
		"cases": 68237,
		"dailyCases": 42,
		"cumuCases": 68237
	},
	{
		"date": "2020-12-27T08:22:06.000Z",
		"cases": 68264,
		"dailyCases": 27,
		"cumuCases": 68264
	},
	{
		"date": "2020-12-28T08:22:37.000Z",
		"cases": 68295,
		"dailyCases": 31,
		"cumuCases": 68295
	},
	{
		"date": "2020-12-29T08:22:34.000Z",
		"cases": 68363,
		"dailyCases": 68,
		"cumuCases": 68363
	},
	{
		"date": "2020-12-30T08:22:49.000Z",
		"cases": 68509,
		"dailyCases": 146,
		"cumuCases": 68509
	},
	{
		"date": "2020-12-31T08:23:07.000Z",
		"cases": 68689,
		"dailyCases": 180,
		"cumuCases": 68689
	},
	{
		"date": "2021-01-01T08:22:33.000Z",
		"cases": 68710,
		"dailyCases": 21,
		"cumuCases": 68710
	},
	{
		"date": "2021-01-02T08:22:52.000Z",
		"cases": 68858,
		"dailyCases": 148,
		"cumuCases": 68858
	},
	{
		"date": "2021-01-03T08:22:02.000Z",
		"cases": 68875,
		"dailyCases": 17,
		"cumuCases": 68875
	},
	{
		"date": "2021-01-04T08:21:49.000Z",
		"cases": 68947,
		"dailyCases": 72,
		"cumuCases": 68947
	},
	{
		"date": "2021-01-05T08:22:16.000Z",
		"cases": 69029,
		"dailyCases": 82,
		"cumuCases": 69029
	},
	{
		"date": "2021-01-06T08:22:03.000Z",
		"cases": 69180,
		"dailyCases": 151,
		"cumuCases": 69180
	},
	{
		"date": "2021-01-07T08:22:42.000Z",
		"cases": 69326,
		"dailyCases": 146,
		"cumuCases": 69326
	},
	{
		"date": "2021-01-08T08:22:18.000Z",
		"cases": 69461,
		"dailyCases": 135,
		"cumuCases": 69461
	},
	{
		"date": "2021-01-09T08:22:12.000Z",
		"cases": 69640,
		"dailyCases": 179,
		"cumuCases": 69640
	},
	{
		"date": "2021-01-10T08:21:50.000Z",
		"cases": 69732,
		"dailyCases": 92,
		"cumuCases": 69732
	},
	{
		"date": "2021-01-11T08:22:15.000Z",
		"cases": 69785,
		"dailyCases": 53,
		"cumuCases": 69785
	},
	{
		"date": "2021-01-12T08:22:15.000Z",
		"cases": 69888,
		"dailyCases": 103,
		"cumuCases": 69888
	},
	{
		"date": "2021-01-13T08:22:32.000Z",
		"cases": 70086,
		"dailyCases": 198,
		"cumuCases": 70086
	},
	{
		"date": "2021-01-14T08:22:24.000Z",
		"cases": 70346,
		"dailyCases": 260,
		"cumuCases": 70346
	},
	{
		"date": "2021-01-15T08:22:40.000Z",
		"cases": 70475,
		"dailyCases": 129,
		"cumuCases": 70475
	},
	{
		"date": "2021-01-16T08:22:17.000Z",
		"cases": 70752,
		"dailyCases": 277,
		"cumuCases": 70752
	},
	{
		"date": "2021-01-17T08:22:34.000Z",
		"cases": 70948,
		"dailyCases": 196,
		"cumuCases": 70948
	},
	{
		"date": "2021-01-18T08:22:15.000Z",
		"cases": 71065,
		"dailyCases": 117,
		"cumuCases": 71065
	},
	{
		"date": "2021-01-19T08:21:54.000Z",
		"cases": 71232,
		"dailyCases": 167,
		"cumuCases": 71232
	},
	{
		"date": "2021-01-20T08:22:01.000Z",
		"cases": 71451,
		"dailyCases": 219,
		"cumuCases": 71451
	},
	{
		"date": "2021-01-21T08:22:10.000Z",
		"cases": 71583,
		"dailyCases": 132,
		"cumuCases": 71583
	},
	{
		"date": "2021-01-22T08:22:03.000Z",
		"cases": 71740,
		"dailyCases": 157,
		"cumuCases": 71740
	},
	{
		"date": "2021-01-23T08:22:35.000Z",
		"cases": 72127,
		"dailyCases": 387,
		"cumuCases": 72127
	},
	{
		"date": "2021-01-24T08:22:16.000Z",
		"cases": 72313,
		"dailyCases": 186,
		"cumuCases": 72313
	},
	{
		"date": "2021-01-25T08:22:02.000Z",
		"cases": 72462,
		"dailyCases": 149,
		"cumuCases": 72462
	},
	{
		"date": "2021-01-26T08:23:41.000Z",
		"cases": 72656,
		"dailyCases": 194,
		"cumuCases": 72656
	},
	{
		"date": "2021-01-27T08:22:24.000Z",
		"cases": 72921,
		"dailyCases": 265,
		"cumuCases": 72921
	},
	{
		"date": "2021-01-28T08:22:23.000Z",
		"cases": 73238,
		"dailyCases": 317,
		"cumuCases": 73238
	},
	{
		"date": "2021-01-29T08:22:49.000Z",
		"cases": 73654,
		"dailyCases": 416,
		"cumuCases": 73654
	},
	{
		"date": "2021-01-30T08:22:42.000Z",
		"cases": 73909,
		"dailyCases": 255,
		"cumuCases": 73909
	},
	{
		"date": "2021-01-31T08:22:53.000Z",
		"cases": 74115,
		"dailyCases": 206,
		"cumuCases": 74115
	},
	{
		"date": "2021-02-01T08:22:49.000Z",
		"cases": 74264,
		"dailyCases": 149,
		"cumuCases": 74264
	},
	{
		"date": "2021-02-02T08:22:52.000Z",
		"cases": 74367,
		"dailyCases": 103,
		"cumuCases": 74367
	},
	{
		"date": "2021-02-03T08:22:26.000Z",
		"cases": 74705,
		"dailyCases": 338,
		"cumuCases": 74705
	},
	{
		"date": "2021-02-04T08:22:38.000Z",
		"cases": 74960,
		"dailyCases": 255,
		"cumuCases": 74960
	},
	{
		"date": "2021-02-05T08:23:55.000Z",
		"cases": 75288,
		"dailyCases": 328,
		"cumuCases": 75288
	},
	{
		"date": "2021-02-06T08:23:00.000Z",
		"cases": 75288,
		"dailyCases": 0,
		"cumuCases": 75288
	},
	{
		"date": "2021-02-07T08:22:39.000Z",
		"cases": 75712,
		"dailyCases": 424,
		"cumuCases": 75712
	},
	{
		"date": "2021-02-08T08:23:30.000Z",
		"cases": 75712,
		"dailyCases": 0,
		"cumuCases": 75712
	},
	{
		"date": "2021-02-09T08:22:41.000Z",
		"cases": 76043,
		"dailyCases": 331,
		"cumuCases": 76043
	},
	{
		"date": "2021-02-10T08:23:55.000Z",
		"cases": 76327,
		"dailyCases": 284,
		"cumuCases": 76327
	},
	{
		"date": "2021-02-11T08:23:29.000Z",
		"cases": 76636,
		"dailyCases": 309,
		"cumuCases": 76636
	},
	{
		"date": "2021-02-12T08:22:12.000Z",
		"cases": 76973,
		"dailyCases": 337,
		"cumuCases": 76973
	},
	{
		"date": "2021-02-13T08:23:43.000Z",
		"cases": 77201,
		"dailyCases": 228,
		"cumuCases": 77201
	},
	{
		"date": "2021-02-14T08:24:49.000Z",
		"cases": 77460,
		"dailyCases": 259,
		"cumuCases": 77460
	},
	{
		"date": "2021-02-15T08:24:38.000Z",
		"cases": 77531,
		"dailyCases": 71,
		"cumuCases": 77531
	},
	{
		"date": "2021-02-16T08:23:10.000Z",
		"cases": 77697,
		"dailyCases": 166,
		"cumuCases": 77697
	},
	{
		"date": "2021-02-17T08:22:58.000Z",
		"cases": 78068,
		"dailyCases": 371,
		"cumuCases": 78068
	},
	{
		"date": "2021-02-18T08:24:16.000Z",
		"cases": 78394,
		"dailyCases": 326,
		"cumuCases": 78394
	},
	{
		"date": "2021-02-19T08:22:51.000Z",
		"cases": 78822,
		"dailyCases": 428,
		"cumuCases": 78822
	},
	{
		"date": "2021-02-20T08:24:33.000Z",
		"cases": 79444,
		"dailyCases": 622,
		"cumuCases": 79444
	},
	{
		"date": "2021-02-21T08:24:21.000Z",
		"cases": 79606,
		"dailyCases": 162,
		"cumuCases": 79606
	},
	{
		"date": "2021-02-22T08:23:41.000Z",
		"cases": 79818,
		"dailyCases": 212,
		"cumuCases": 79818
	},
	{
		"date": "2021-02-23T08:29:16.000Z",
		"cases": 80097,
		"dailyCases": 279,
		"cumuCases": 80097
	},
	{
		"date": "2021-02-24T08:24:57.000Z",
		"cases": 80472,
		"dailyCases": 375,
		"cumuCases": 80472
	},
	{
		"date": "2021-02-25T08:22:40.000Z",
		"cases": 80923,
		"dailyCases": 451,
		"cumuCases": 80923
	},
	{
		"date": "2021-02-26T08:22:28.000Z",
		"cases": 81281,
		"dailyCases": 358,
		"cumuCases": 81281
	},
	{
		"date": "2021-02-27T08:22:20.000Z",
		"cases": 81776,
		"dailyCases": 495,
		"cumuCases": 81776
	},
	{
		"date": "2021-02-28T08:23:01.000Z",
		"cases": 82049,
		"dailyCases": 273,
		"cumuCases": 82049
	},
	{
		"date": "2021-03-01T08:23:30.000Z",
		"cases": 82126,
		"dailyCases": 77,
		"cumuCases": 82126
	},
	{
		"date": "2021-03-02T08:23:28.000Z",
		"cases": 82217,
		"dailyCases": 91,
		"cumuCases": 82217
	},
	{
		"date": "2021-03-03T08:24:24.000Z",
		"cases": 82612,
		"dailyCases": 395,
		"cumuCases": 82612
	},
	{
		"date": "2021-03-04T08:26:29.000Z",
		"cases": 83097,
		"dailyCases": 485,
		"cumuCases": 83097
	},
	{
		"date": "2021-03-05T07:23:41.000Z",
		"cases": 83452,
		"dailyCases": 355,
		"cumuCases": 83452
	},
	{
		"date": "2021-03-06T08:21:54.000Z",
		"cases": 83745,
		"dailyCases": 293,
		"cumuCases": 83745
	},
	{
		"date": "2021-03-07T08:24:48.000Z",
		"cases": 83846,
		"dailyCases": 101,
		"cumuCases": 83846
	},
	{
		"date": "2021-03-08T08:28:19.000Z",
		"cases": 83869,
		"dailyCases": 23,
		"cumuCases": 83869
	},
	{
		"date": "2021-03-09T08:24:35.000Z",
		"cases": 83869,
		"dailyCases": 0,
		"cumuCases": 83869
	},
	{
		"date": "2021-03-10T08:25:48.000Z",
		"cases": 83922,
		"dailyCases": 53,
		"cumuCases": 83922
	},
	{
		"date": "2021-03-11T08:26:50.000Z",
		"cases": 84909,
		"dailyCases": 987,
		"cumuCases": 84909
	},
	{
		"date": "2021-03-12T08:25:15.000Z",
		"cases": 85242,
		"dailyCases": 333,
		"cumuCases": 85242
	},
	{
		"date": "2021-03-13T08:25:37.000Z",
		"cases": 85572,
		"dailyCases": 330,
		"cumuCases": 85572
	},
	{
		"date": "2021-03-14T08:25:51.000Z",
		"cases": 85767,
		"dailyCases": 195,
		"cumuCases": 85767
	},
	{
		"date": "2021-03-15T08:25:13.000Z",
		"cases": 85856,
		"dailyCases": 89,
		"cumuCases": 85856
	},
	{
		"date": "2021-03-16T08:25:07.000Z",
		"cases": 86022,
		"dailyCases": 166,
		"cumuCases": 86022
	},
	{
		"date": "2021-03-17T08:26:22.000Z",
		"cases": 86382,
		"dailyCases": 360,
		"cumuCases": 86382
	},
	{
		"date": "2021-03-18T08:26:09.000Z",
		"cases": 86683,
		"dailyCases": 301,
		"cumuCases": 86683
	},
	{
		"date": "2021-03-19T08:25:46.000Z",
		"cases": 87032,
		"dailyCases": 349,
		"cumuCases": 87032
	},
	{
		"date": "2021-03-20T08:25:44.000Z",
		"cases": 87354,
		"dailyCases": 322,
		"cumuCases": 87354
	},
	{
		"date": "2021-03-21T08:25:43.000Z",
		"cases": 87554,
		"dailyCases": 200,
		"cumuCases": 87554
	},
	{
		"date": "2021-03-22T08:26:18.000Z",
		"cases": 87649,
		"dailyCases": 95,
		"cumuCases": 87649
	},
	{
		"date": "2021-03-23T08:25:40.000Z",
		"cases": 87866,
		"dailyCases": 217,
		"cumuCases": 87866
	},
	{
		"date": "2021-03-24T08:27:00.000Z",
		"cases": 88157,
		"dailyCases": 291,
		"cumuCases": 88157
	},
	{
		"date": "2021-03-25T08:26:55.000Z",
		"cases": 88458,
		"dailyCases": 301,
		"cumuCases": 88458
	},
	{
		"date": "2021-03-26T08:25:04.000Z",
		"cases": 88707,
		"dailyCases": 249,
		"cumuCases": 88707
	},
	{
		"date": "2021-03-27T08:28:10.000Z",
		"cases": 88980,
		"dailyCases": 273,
		"cumuCases": 88980
	},
	{
		"date": "2021-03-28T07:28:35.000Z",
		"cases": 89116,
		"dailyCases": 136,
		"cumuCases": 89116
	},
	{
		"date": "2021-03-29T07:26:23.000Z",
		"cases": 89164,
		"dailyCases": 48,
		"cumuCases": 89164
	},
	{
		"date": "2021-03-30T07:26:25.000Z",
		"cases": 89164,
		"dailyCases": 0,
		"cumuCases": 89164
	},
	{
		"date": "2021-03-31T07:27:05.000Z",
		"cases": 89525,
		"dailyCases": 361,
		"cumuCases": 89525
	},
	{
		"date": "2021-04-01T07:20:36.000Z",
		"cases": 89853,
		"dailyCases": 328,
		"cumuCases": 89853
	},
	{
		"date": "2021-04-02T07:20:44.000Z",
		"cases": 90109,
		"dailyCases": 256,
		"cumuCases": 90109
	},
	{
		"date": "2021-04-03T07:20:49.000Z",
		"cases": 90276,
		"dailyCases": 167,
		"cumuCases": 90276
	},
	{
		"date": "2021-04-04T07:20:35.000Z",
		"cases": 90350,
		"dailyCases": 74,
		"cumuCases": 90350
	},
	{
		"date": "2021-04-05T07:20:32.000Z",
		"cases": 90371,
		"dailyCases": 21,
		"cumuCases": 90371
	},
	{
		"date": "2021-04-06T07:20:53.000Z",
		"cases": 90582,
		"dailyCases": 211,
		"cumuCases": 90582
	},
	{
		"date": "2021-04-07T07:21:13.000Z",
		"cases": 90765,
		"dailyCases": 183,
		"cumuCases": 90765
	},
	{
		"date": "2021-04-08T07:21:13.000Z",
		"cases": 91036,
		"dailyCases": 271,
		"cumuCases": 91036
	},
	{
		"date": "2021-04-09T07:20:59.000Z",
		"cases": 91302,
		"dailyCases": 266,
		"cumuCases": 91302
	},
	{
		"date": "2021-04-10T07:20:56.000Z",
		"cases": 91616,
		"dailyCases": 314,
		"cumuCases": 91616
	},
	{
		"date": "2021-04-11T07:21:00.000Z",
		"cases": 91782,
		"dailyCases": 166,
		"cumuCases": 91782
	},
	{
		"date": "2021-04-12T07:20:37.000Z",
		"cases": 91849,
		"dailyCases": 67,
		"cumuCases": 91849
	},
	{
		"date": "2021-04-13T07:20:41.000Z",
		"cases": 92099,
		"dailyCases": 250,
		"cumuCases": 92099
	},
	{
		"date": "2021-04-14T07:20:54.000Z",
		"cases": 92512,
		"dailyCases": 413,
		"cumuCases": 92512
	},
	{
		"date": "2021-04-15T07:20:46.000Z",
		"cases": 92902,
		"dailyCases": 390,
		"cumuCases": 92902
	},
	{
		"date": "2021-04-16T07:20:40.000Z",
		"cases": 93259,
		"dailyCases": 357,
		"cumuCases": 93259
	},
	{
		"date": "2021-04-17T07:20:41.000Z",
		"cases": 93574,
		"dailyCases": 315,
		"cumuCases": 93574
	},
	{
		"date": "2021-04-18T07:20:57.000Z",
		"cases": 93752,
		"dailyCases": 178,
		"cumuCases": 93752
	},
	{
		"date": "2021-04-19T07:20:41.000Z",
		"cases": 93790,
		"dailyCases": 38,
		"cumuCases": 93790
	},
	{
		"date": "2021-04-20T07:21:14.000Z",
		"cases": 93957,
		"dailyCases": 167,
		"cumuCases": 93957
	},
	{
		"date": "2021-04-21T07:20:53.000Z",
		"cases": 94270,
		"dailyCases": 313,
		"cumuCases": 94270
	},
	{
		"date": "2021-04-22T07:20:52.000Z",
		"cases": 94566,
		"dailyCases": 296,
		"cumuCases": 94566
	},
	{
		"date": "2021-04-23T07:20:38.000Z",
		"cases": 94769,
		"dailyCases": 203,
		"cumuCases": 94769
	},
	{
		"date": "2021-04-24T07:20:32.000Z",
		"cases": 95027,
		"dailyCases": 258,
		"cumuCases": 95027
	},
	{
		"date": "2021-04-25T07:21:04.000Z",
		"cases": 95223,
		"dailyCases": 196,
		"cumuCases": 95223
	},
	{
		"date": "2021-04-26T07:20:52.000Z",
		"cases": 95308,
		"dailyCases": 85,
		"cumuCases": 95308
	},
	{
		"date": "2021-04-27T07:20:32.000Z",
		"cases": 95484,
		"dailyCases": 176,
		"cumuCases": 95484
	},
	{
		"date": "2021-04-28T07:20:55.000Z",
		"cases": 95735,
		"dailyCases": 251,
		"cumuCases": 95735
	},
	{
		"date": "2021-04-29T07:21:03.000Z",
		"cases": 95983,
		"dailyCases": 248,
		"cumuCases": 95983
	},
	{
		"date": "2021-04-30T07:20:47.000Z",
		"cases": 96316,
		"dailyCases": 333,
		"cumuCases": 96316
	},
	{
		"date": "2021-05-01T07:20:48.000Z",
		"cases": 96576,
		"dailyCases": 260,
		"cumuCases": 96576
	},
	{
		"date": "2021-05-02T07:20:39.000Z",
		"cases": 96732,
		"dailyCases": 156,
		"cumuCases": 96732
	},
	{
		"date": "2021-05-03T07:20:34.000Z",
		"cases": 96771,
		"dailyCases": 39,
		"cumuCases": 96771
	},
	{
		"date": "2021-05-04T07:20:43.000Z",
		"cases": 96966,
		"dailyCases": 195,
		"cumuCases": 96966
	},
	{
		"date": "2021-05-05T07:20:38.000Z",
		"cases": 97212,
		"dailyCases": 246,
		"cumuCases": 97212
	},
	{
		"date": "2021-05-06T07:20:40.000Z",
		"cases": 97540,
		"dailyCases": 328,
		"cumuCases": 97540
	},
	{
		"date": "2021-05-07T07:21:04.000Z",
		"cases": 97913,
		"dailyCases": 373,
		"cumuCases": 97913
	},
	{
		"date": "2021-05-08T07:20:35.000Z",
		"cases": 98152,
		"dailyCases": 239,
		"cumuCases": 98152
	},
	{
		"date": "2021-05-09T07:20:38.000Z",
		"cases": 98343,
		"dailyCases": 191,
		"cumuCases": 98343
	},
	{
		"date": "2021-05-10T07:20:41.000Z",
		"cases": 98372,
		"dailyCases": 29,
		"cumuCases": 98372
	},
	{
		"date": "2021-05-11T07:21:29.000Z",
		"cases": 98575,
		"dailyCases": 203,
		"cumuCases": 98575
	},
	{
		"date": "2021-05-12T07:20:51.000Z",
		"cases": 98875,
		"dailyCases": 300,
		"cumuCases": 98875
	},
	{
		"date": "2021-05-13T07:20:41.000Z",
		"cases": 99155,
		"dailyCases": 280,
		"cumuCases": 99155
	},
	{
		"date": "2021-05-14T07:20:58.000Z",
		"cases": 99459,
		"dailyCases": 304,
		"cumuCases": 99459
	},
	{
		"date": "2021-05-15T07:20:49.000Z",
		"cases": 99768,
		"dailyCases": 309,
		"cumuCases": 99768
	},
	{
		"date": "2021-05-16T07:20:34.000Z",
		"cases": 99768,
		"dailyCases": 0,
		"cumuCases": 99768
	},
	{
		"date": "2021-05-17T07:20:33.000Z",
		"cases": 100084,
		"dailyCases": 316,
		"cumuCases": 100084
	},
	{
		"date": "2021-05-18T07:20:42.000Z",
		"cases": 100254,
		"dailyCases": 170,
		"cumuCases": 100254
	},
	{
		"date": "2021-05-19T07:21:05.000Z",
		"cases": 100700,
		"dailyCases": 446,
		"cumuCases": 100700
	},
	{
		"date": "2021-05-20T07:20:43.000Z",
		"cases": 101004,
		"dailyCases": 304,
		"cumuCases": 101004
	},
	{
		"date": "2021-05-21T07:20:45.000Z",
		"cases": 101398,
		"dailyCases": 394,
		"cumuCases": 101398
	},
	{
		"date": "2021-05-22T07:20:51.000Z",
		"cases": 101797,
		"dailyCases": 399,
		"cumuCases": 101797
	},
	{
		"date": "2021-05-23T07:20:53.000Z",
		"cases": 102019,
		"dailyCases": 222,
		"cumuCases": 102019
	},
	{
		"date": "2021-05-24T07:21:08.000Z",
		"cases": 102102,
		"dailyCases": 83,
		"cumuCases": 102102
	},
	{
		"date": "2021-05-25T07:20:35.000Z",
		"cases": 102289,
		"dailyCases": 187,
		"cumuCases": 102289
	},
	{
		"date": "2021-05-26T07:20:59.000Z",
		"cases": 102582,
		"dailyCases": 293,
		"cumuCases": 102582
	},
	{
		"date": "2021-05-27T07:20:36.000Z",
		"cases": 102812,
		"dailyCases": 230,
		"cumuCases": 102812
	},
	{
		"date": "2021-05-28T07:20:41.000Z",
		"cases": 102930,
		"dailyCases": 118,
		"cumuCases": 102930
	},
	{
		"date": "2021-05-29T07:20:55.000Z",
		"cases": 103222,
		"dailyCases": 292,
		"cumuCases": 103222
	},
	{
		"date": "2021-05-30T06:08:59.000Z",
		"cases": 103423,
		"dailyCases": 201,
		"cumuCases": 103423
	},
	{
		"date": "2021-05-31T07:23:09.000Z",
		"cases": 103506,
		"dailyCases": 83,
		"cumuCases": 103506
	},
	{
		"date": "2021-06-01T07:24:34.000Z",
		"cases": 103836,
		"dailyCases": 330,
		"cumuCases": 103836
	},
	{
		"date": "2021-06-02T07:23:32.000Z",
		"cases": 104182,
		"dailyCases": 346,
		"cumuCases": 104182
	},
	{
		"date": "2021-06-03T07:23:37.000Z",
		"cases": 104504,
		"dailyCases": 322,
		"cumuCases": 104504
	},
	{
		"date": "2021-06-04T07:23:03.000Z",
		"cases": 104588,
		"dailyCases": 84,
		"cumuCases": 104588
	},
	{
		"date": "2021-06-05T07:24:03.000Z",
		"cases": 105032,
		"dailyCases": 444,
		"cumuCases": 105032
	},
	{
		"date": "2021-06-06T07:22:51.000Z",
		"cases": 105230,
		"dailyCases": 198,
		"cumuCases": 105230
	},
	{
		"date": "2021-06-07T07:22:35.000Z",
		"cases": 105373,
		"dailyCases": 143,
		"cumuCases": 105373
	},
	{
		"date": "2021-06-08T07:23:31.000Z",
		"cases": 105425,
		"dailyCases": 52,
		"cumuCases": 105425
	},
	{
		"date": "2021-06-09T07:23:17.000Z",
		"cases": 105445,
		"dailyCases": 20,
		"cumuCases": 105445
	},
	{
		"date": "2021-06-10T07:23:20.000Z",
		"cases": 105517,
		"dailyCases": 72,
		"cumuCases": 105517
	},
	{
		"date": "2021-06-11T07:22:22.000Z",
		"cases": 106895,
		"dailyCases": 1378,
		"cumuCases": 106895
	},
	{
		"date": "2021-06-12T07:22:44.000Z",
		"cases": 107348,
		"dailyCases": 453,
		"cumuCases": 107348
	},
	{
		"date": "2021-06-13T07:22:46.000Z",
		"cases": 107570,
		"dailyCases": 222,
		"cumuCases": 107570
	},
	{
		"date": "2021-06-14T07:22:22.000Z",
		"cases": 107646,
		"dailyCases": 76,
		"cumuCases": 107646
	},
	{
		"date": "2021-06-15T07:22:32.000Z",
		"cases": 107872,
		"dailyCases": 226,
		"cumuCases": 107872
	},
	{
		"date": "2021-06-16T07:22:36.000Z",
		"cases": 108358,
		"dailyCases": 486,
		"cumuCases": 108358
	},
	{
		"date": "2021-06-17T07:22:16.000Z",
		"cases": 108704,
		"dailyCases": 346,
		"cumuCases": 108704
	},
	{
		"date": "2021-06-18T07:22:33.000Z",
		"cases": 109094,
		"dailyCases": 390,
		"cumuCases": 109094
	},
	{
		"date": "2021-06-19T07:21:48.000Z",
		"cases": 109444,
		"dailyCases": 350,
		"cumuCases": 109444
	},
	{
		"date": "2021-06-20T07:21:41.000Z",
		"cases": 109650,
		"dailyCases": 206,
		"cumuCases": 109650
	},
	{
		"date": "2021-06-21T07:21:34.000Z",
		"cases": 109702,
		"dailyCases": 52,
		"cumuCases": 109702
	},
	{
		"date": "2021-06-22T07:21:46.000Z",
		"cases": 109724,
		"dailyCases": 22,
		"cumuCases": 109724
	},
	{
		"date": "2021-06-23T07:21:55.000Z",
		"cases": 109781,
		"dailyCases": 57,
		"cumuCases": 109781
	},
	{
		"date": "2021-06-24T07:21:33.000Z",
		"cases": 110820,
		"dailyCases": 1039,
		"cumuCases": 110820
	},
	{
		"date": "2021-06-25T07:21:43.000Z",
		"cases": 111108,
		"dailyCases": 288,
		"cumuCases": 111108
	},
	{
		"date": "2021-06-26T07:21:39.000Z",
		"cases": 111436,
		"dailyCases": 328,
		"cumuCases": 111436
	},
	{
		"date": "2021-06-27T07:21:29.000Z",
		"cases": 111720,
		"dailyCases": 284,
		"cumuCases": 111720
	},
	{
		"date": "2021-06-28T07:21:28.000Z",
		"cases": 111844,
		"dailyCases": 124,
		"cumuCases": 111844
	},
	{
		"date": "2021-06-29T07:21:41.000Z",
		"cases": 111858,
		"dailyCases": 14,
		"cumuCases": 111858
	},
	{
		"date": "2021-06-30T07:21:19.000Z",
		"cases": 112133,
		"dailyCases": 275,
		"cumuCases": 112133
	},
	{
		"date": "2021-07-01T07:21:47.000Z",
		"cases": 112643,
		"dailyCases": 510,
		"cumuCases": 112643
	},
	{
		"date": "2021-07-02T07:21:37.000Z",
		"cases": 112927,
		"dailyCases": 284,
		"cumuCases": 112927
	},
	{
		"date": "2021-07-03T07:21:38.000Z",
		"cases": 113277,
		"dailyCases": 350,
		"cumuCases": 113277
	},
	{
		"date": "2021-07-04T07:21:28.000Z",
		"cases": 113499,
		"dailyCases": 222,
		"cumuCases": 113499
	},
	{
		"date": "2021-07-05T07:21:32.000Z",
		"cases": 113568,
		"dailyCases": 69,
		"cumuCases": 113568
	},
	{
		"date": "2021-07-06T07:21:20.000Z",
		"cases": 113758,
		"dailyCases": 190,
		"cumuCases": 113758
	},
	{
		"date": "2021-07-07T07:21:26.000Z",
		"cases": 114105,
		"dailyCases": 347,
		"cumuCases": 114105
	},
	{
		"date": "2021-07-08T07:21:21.000Z",
		"cases": 114483,
		"dailyCases": 378,
		"cumuCases": 114483
	},
	{
		"date": "2021-07-09T07:21:25.000Z",
		"cases": 114714,
		"dailyCases": 231,
		"cumuCases": 114714
	},
	{
		"date": "2021-07-10T07:21:43.000Z",
		"cases": 115110,
		"dailyCases": 396,
		"cumuCases": 115110
	},
	{
		"date": "2021-07-11T07:21:34.000Z",
		"cases": 115284,
		"dailyCases": 174,
		"cumuCases": 115284
	},
	{
		"date": "2021-07-12T07:21:18.000Z",
		"cases": 115419,
		"dailyCases": 135,
		"cumuCases": 115419
	},
	{
		"date": "2021-07-13T07:21:35.000Z",
		"cases": 115483,
		"dailyCases": 64,
		"cumuCases": 115483
	},
	{
		"date": "2021-07-14T07:21:48.000Z",
		"cases": 115829,
		"dailyCases": 346,
		"cumuCases": 115829
	},
	{
		"date": "2021-07-15T07:21:22.000Z",
		"cases": 115829,
		"dailyCases": 0,
		"cumuCases": 115829
	},
	{
		"date": "2021-07-16T07:22:22.000Z",
		"cases": 116561,
		"dailyCases": 732,
		"cumuCases": 116561
	},
	{
		"date": "2021-07-17T07:22:07.000Z",
		"cases": 116950,
		"dailyCases": 389,
		"cumuCases": 116950
	},
	{
		"date": "2021-07-18T07:21:24.000Z",
		"cases": 117209,
		"dailyCases": 259,
		"cumuCases": 117209
	},
	{
		"date": "2021-07-19T07:21:48.000Z",
		"cases": 117266,
		"dailyCases": 57,
		"cumuCases": 117266
	},
	{
		"date": "2021-07-20T07:21:40.000Z",
		"cases": 117316,
		"dailyCases": 50,
		"cumuCases": 117316
	},
	{
		"date": "2021-07-21T07:21:19.000Z",
		"cases": 117670,
		"dailyCases": 354,
		"cumuCases": 117670
	},
	{
		"date": "2021-07-22T07:21:29.000Z",
		"cases": 118036,
		"dailyCases": 366,
		"cumuCases": 118036
	},
	{
		"date": "2021-07-23T03:21:36.000Z",
		"cases": 118338,
		"dailyCases": 302,
		"cumuCases": 118338
	},
	{
		"date": "2021-07-24T07:22:12.000Z",
		"cases": 118502,
		"dailyCases": 164,
		"cumuCases": 118502
	},
	{
		"date": "2021-07-25T07:21:28.000Z",
		"cases": 118766,
		"dailyCases": 264,
		"cumuCases": 118766
	},
	{
		"date": "2021-07-26T07:21:18.000Z",
		"cases": 118818,
		"dailyCases": 52,
		"cumuCases": 118818
	},
	{
		"date": "2021-07-27T07:21:39.000Z",
		"cases": 118968,
		"dailyCases": 150,
		"cumuCases": 118968
	},
	{
		"date": "2021-07-28T07:21:33.000Z",
		"cases": 119261,
		"dailyCases": 293,
		"cumuCases": 119261
	},
	{
		"date": "2021-07-29T07:21:34.000Z",
		"cases": 119572,
		"dailyCases": 311,
		"cumuCases": 119572
	},
	{
		"date": "2021-07-30T07:21:35.000Z",
		"cases": 119828,
		"dailyCases": 256,
		"cumuCases": 119828
	},
	{
		"date": "2021-07-31T07:21:50.000Z",
		"cases": 120005,
		"dailyCases": 177,
		"cumuCases": 120005
	},
	{
		"date": "2021-08-01T07:21:36.000Z",
		"cases": 120121,
		"dailyCases": 116,
		"cumuCases": 120121
	},
	{
		"date": "2021-08-02T07:21:39.000Z",
		"cases": 120159,
		"dailyCases": 38,
		"cumuCases": 120159
	},
	{
		"date": "2021-08-03T07:21:25.000Z",
		"cases": 120252,
		"dailyCases": 93,
		"cumuCases": 120252
	},
	{
		"date": "2021-08-04T07:21:51.000Z",
		"cases": 120410,
		"dailyCases": 158,
		"cumuCases": 120410
	},
	{
		"date": "2021-08-05T07:21:18.000Z",
		"cases": 120590,
		"dailyCases": 180,
		"cumuCases": 120590
	},
	{
		"date": "2021-08-06T07:21:30.000Z",
		"cases": 120750,
		"dailyCases": 160,
		"cumuCases": 120750
	},
	{
		"date": "2021-08-07T07:21:33.000Z",
		"cases": 120905,
		"dailyCases": 155,
		"cumuCases": 120905
	},
	{
		"date": "2021-08-08T07:21:24.000Z",
		"cases": 121012,
		"dailyCases": 107,
		"cumuCases": 121012
	},
	{
		"date": "2021-08-09T07:21:27.000Z",
		"cases": 121043,
		"dailyCases": 31,
		"cumuCases": 121043
	},
	{
		"date": "2021-08-10T07:21:58.000Z",
		"cases": 121130,
		"dailyCases": 87,
		"cumuCases": 121130
	},
	{
		"date": "2021-08-11T07:21:25.000Z",
		"cases": 121315,
		"dailyCases": 185,
		"cumuCases": 121315
	},
	{
		"date": "2021-08-12T07:21:24.000Z",
		"cases": 121481,
		"dailyCases": 166,
		"cumuCases": 121481
	},
	{
		"date": "2021-08-13T07:21:25.000Z",
		"cases": 121666,
		"dailyCases": 185,
		"cumuCases": 121666
	},
	{
		"date": "2021-08-14T07:21:41.000Z",
		"cases": 121697,
		"dailyCases": 31,
		"cumuCases": 121697
	},
	{
		"date": "2021-08-15T07:21:31.000Z",
		"cases": 121908,
		"dailyCases": 211,
		"cumuCases": 121908
	},
	{
		"date": "2021-08-16T07:21:49.000Z",
		"cases": 121940,
		"dailyCases": 32,
		"cumuCases": 121940
	},
	{
		"date": "2021-08-17T07:21:35.000Z",
		"cases": 122064,
		"dailyCases": 124,
		"cumuCases": 122064
	},
	{
		"date": "2021-08-18T07:21:15.000Z",
		"cases": 122224,
		"dailyCases": 160,
		"cumuCases": 122224
	},
	{
		"date": "2021-08-19T07:21:33.000Z",
		"cases": 122373,
		"dailyCases": 149,
		"cumuCases": 122373
	},
	{
		"date": "2021-08-20T07:21:38.000Z",
		"cases": 122638,
		"dailyCases": 265,
		"cumuCases": 122638
	},
	{
		"date": "2021-08-21T07:21:29.000Z",
		"cases": 122831,
		"dailyCases": 193,
		"cumuCases": 122831
	},
	{
		"date": "2021-08-22T07:21:27.000Z",
		"cases": 122960,
		"dailyCases": 129,
		"cumuCases": 122960
	},
	{
		"date": "2021-08-23T07:21:19.000Z",
		"cases": 122975,
		"dailyCases": 15,
		"cumuCases": 122975
	},
	{
		"date": "2021-08-24T07:21:41.000Z",
		"cases": 123095,
		"dailyCases": 120,
		"cumuCases": 123095
	},
	{
		"date": "2021-08-25T07:21:28.000Z",
		"cases": 123121,
		"dailyCases": 26,
		"cumuCases": 123121
	},
	{
		"date": "2021-08-26T07:21:37.000Z",
		"cases": 123394,
		"dailyCases": 273,
		"cumuCases": 123394
	},
	{
		"date": "2021-08-27T07:21:28.000Z",
		"cases": 123461,
		"dailyCases": 67,
		"cumuCases": 123461
	},
	{
		"date": "2021-08-28T07:21:14.000Z",
		"cases": 123662,
		"dailyCases": 201,
		"cumuCases": 123662
	},
	{
		"date": "2021-08-29T07:21:23.000Z",
		"cases": 123735,
		"dailyCases": 73,
		"cumuCases": 123735
	},
	{
		"date": "2021-08-30T07:21:46.000Z",
		"cases": 123749,
		"dailyCases": 14,
		"cumuCases": 123749
	},
	{
		"date": "2021-08-31T07:21:38.000Z",
		"cases": 123816,
		"dailyCases": 67,
		"cumuCases": 123816
	},
	{
		"date": "2021-09-01T07:21:15.000Z",
		"cases": 123990,
		"dailyCases": 174,
		"cumuCases": 123990
	},
	{
		"date": "2021-09-02T07:21:20.000Z",
		"cases": 124092,
		"dailyCases": 102,
		"cumuCases": 124092
	},
	{
		"date": "2021-09-03T07:21:28.000Z",
		"cases": 124214,
		"dailyCases": 122,
		"cumuCases": 124214
	},
	{
		"date": "2021-09-04T07:21:33.000Z",
		"cases": 124293,
		"dailyCases": 79,
		"cumuCases": 124293
	},
	{
		"date": "2021-09-05T07:21:22.000Z",
		"cases": 124429,
		"dailyCases": 136,
		"cumuCases": 124429
	},
	{
		"date": "2021-09-06T07:21:35.000Z",
		"cases": 124441,
		"dailyCases": 12,
		"cumuCases": 124441
	},
	{
		"date": "2021-09-07T07:21:31.000Z",
		"cases": 124441,
		"dailyCases": 0,
		"cumuCases": 124441
	},
	{
		"date": "2021-09-08T07:21:27.000Z",
		"cases": 124453,
		"dailyCases": 12,
		"cumuCases": 124453
	},
	{
		"date": "2021-09-09T07:21:20.000Z",
		"cases": 124453,
		"dailyCases": 0,
		"cumuCases": 124453
	},
	{
		"date": "2021-09-10T07:21:30.000Z",
		"cases": 124477,
		"dailyCases": 24,
		"cumuCases": 124477
	},
	{
		"date": "2021-09-11T07:21:13.000Z",
		"cases": 124482,
		"dailyCases": 5,
		"cumuCases": 124482
	},
	{
		"date": "2021-09-12T07:21:15.000Z",
		"cases": 126832,
		"dailyCases": 2350,
		"cumuCases": 126832
	},
	{
		"date": "2021-09-13T07:21:41.000Z",
		"cases": 126855,
		"dailyCases": 23,
		"cumuCases": 126855
	},
	{
		"date": "2021-09-14T06:22:37.000Z",
		"cases": 126855,
		"dailyCases": 0,
		"cumuCases": 126855
	},
	{
		"date": "2021-09-15T07:22:19.000Z",
		"cases": 125838,
		"dailyCases": -1017,
		"cumuCases": 125838
	},
	{
		"date": "2021-09-16T07:21:46.000Z",
		"cases": 125840,
		"dailyCases": 2,
		"cumuCases": 125840
	},
	{
		"date": "2021-09-17T07:21:24.000Z",
		"cases": 125866,
		"dailyCases": 26,
		"cumuCases": 125866
	},
	{
		"date": "2021-09-18T07:21:34.000Z",
		"cases": 126086,
		"dailyCases": 220,
		"cumuCases": 126086
	},
	{
		"date": "2021-09-19T07:21:22.000Z",
		"cases": 126095,
		"dailyCases": 9,
		"cumuCases": 126095
	},
	{
		"date": "2021-09-20T07:21:26.000Z",
		"cases": 126097,
		"dailyCases": 2,
		"cumuCases": 126097
	},
	{
		"date": "2021-09-21T07:21:45.000Z",
		"cases": 126100,
		"dailyCases": 3,
		"cumuCases": 126100
	},
	{
		"date": "2021-09-22T07:21:43.000Z",
		"cases": 126108,
		"dailyCases": 8,
		"cumuCases": 126108
	},
	{
		"date": "2021-09-23T07:21:44.000Z",
		"cases": 126114,
		"dailyCases": 6,
		"cumuCases": 126114
	},
	{
		"date": "2021-09-24T07:21:31.000Z",
		"cases": 126136,
		"dailyCases": 22,
		"cumuCases": 126136
	},
	{
		"date": "2021-09-25T07:21:29.000Z",
		"cases": 126167,
		"dailyCases": 31,
		"cumuCases": 126167
	},
	{
		"date": "2021-09-26T07:21:16.000Z",
		"cases": 126187,
		"dailyCases": 20,
		"cumuCases": 126187
	},
	{
		"date": "2021-09-27T07:21:28.000Z",
		"cases": 126188,
		"dailyCases": 1,
		"cumuCases": 126188
	},
	{
		"date": "2021-09-28T07:21:45.000Z",
		"cases": 126191,
		"dailyCases": 3,
		"cumuCases": 126191
	},
	{
		"date": "2021-09-29T07:21:20.000Z",
		"cases": 126199,
		"dailyCases": 8,
		"cumuCases": 126199
	},
	{
		"date": "2021-09-30T07:21:35.000Z",
		"cases": 126212,
		"dailyCases": 13,
		"cumuCases": 126212
	},
	{
		"date": "2021-10-01T07:21:25.000Z",
		"cases": 126220,
		"dailyCases": 8,
		"cumuCases": 126220
	},
	{
		"date": "2021-10-02T07:21:24.000Z",
		"cases": 126234,
		"dailyCases": 14,
		"cumuCases": 126234
	},
	{
		"date": "2021-10-03T07:21:31.000Z",
		"cases": 126236,
		"dailyCases": 2,
		"cumuCases": 126236
	},
	{
		"date": "2021-10-04T07:21:27.000Z",
		"cases": 126236,
		"dailyCases": 0,
		"cumuCases": 126236
	},
	{
		"date": "2021-10-05T07:21:33.000Z",
		"cases": 126238,
		"dailyCases": 2,
		"cumuCases": 126238
	},
	{
		"date": "2021-10-06T07:21:36.000Z",
		"cases": 126238,
		"dailyCases": 0,
		"cumuCases": 126238
	},
	{
		"date": "2021-10-07T07:21:25.000Z",
		"cases": 126238,
		"dailyCases": 0,
		"cumuCases": 126238
	},
	{
		"date": "2021-10-08T07:21:34.000Z",
		"cases": 126243,
		"dailyCases": 5,
		"cumuCases": 126243
	},
	{
		"date": "2021-10-09T07:21:38.000Z",
		"cases": 126259,
		"dailyCases": 16,
		"cumuCases": 126259
	},
	{
		"date": "2021-10-10T07:21:31.000Z",
		"cases": 126269,
		"dailyCases": 10,
		"cumuCases": 126269
	},
	{
		"date": "2021-10-11T07:21:09.000Z",
		"cases": 126273,
		"dailyCases": 4,
		"cumuCases": 126273
	},
	{
		"date": "2021-10-12T07:20:51.000Z",
		"cases": 126280,
		"dailyCases": 7,
		"cumuCases": 126280
	},
	{
		"date": "2021-10-13T07:21:29.000Z",
		"cases": 126280,
		"dailyCases": 0,
		"cumuCases": 126280
	},
	{
		"date": "2021-10-14T07:21:26.000Z",
		"cases": 126289,
		"dailyCases": 9,
		"cumuCases": 126289
	},
	{
		"date": "2021-10-15T07:21:15.000Z",
		"cases": 126300,
		"dailyCases": 11,
		"cumuCases": 126300
	},
	{
		"date": "2021-10-16T07:21:29.000Z",
		"cases": 126305,
		"dailyCases": 5,
		"cumuCases": 126305
	},
	{
		"date": "2021-10-17T07:21:10.000Z",
		"cases": 126305,
		"dailyCases": 0,
		"cumuCases": 126305
	},
	{
		"date": "2021-10-18T07:20:54.000Z",
		"cases": 126316,
		"dailyCases": 11,
		"cumuCases": 126316
	},
	{
		"date": "2021-10-19T07:21:00.000Z",
		"cases": 126941,
		"dailyCases": 625,
		"cumuCases": 126941
	},
	{
		"date": "2021-10-20T07:21:18.000Z",
		"cases": 127010,
		"dailyCases": 69,
		"cumuCases": 127010
	},
	{
		"date": "2021-10-21T07:21:14.000Z",
		"cases": 127047,
		"dailyCases": 37,
		"cumuCases": 127047
	},
	{
		"date": "2021-10-22T07:21:32.000Z",
		"cases": 127106,
		"dailyCases": 59,
		"cumuCases": 127106
	},
	{
		"date": "2021-10-23T07:21:22.000Z",
		"cases": 127154,
		"dailyCases": 48,
		"cumuCases": 127154
	},
	{
		"date": "2021-10-24T07:22:31.000Z",
		"cases": 127191,
		"dailyCases": 37,
		"cumuCases": 127191
	},
	{
		"date": "2021-10-25T07:22:09.000Z",
		"cases": 127203,
		"dailyCases": 12,
		"cumuCases": 127203
	},
	{
		"date": "2021-10-26T07:22:32.000Z",
		"cases": 127240,
		"dailyCases": 37,
		"cumuCases": 127240
	},
	{
		"date": "2021-10-27T07:22:08.000Z",
		"cases": 127278,
		"dailyCases": 38,
		"cumuCases": 127278
	},
	{
		"date": "2021-10-28T07:22:03.000Z",
		"cases": 127319,
		"dailyCases": 41,
		"cumuCases": 127319
	},
	{
		"date": "2021-10-29T07:22:03.000Z",
		"cases": 127357,
		"dailyCases": 38,
		"cumuCases": 127357
	},
	{
		"date": "2021-10-30T07:22:08.000Z",
		"cases": 127372,
		"dailyCases": 15,
		"cumuCases": 127372
	}
]